atri_utils/__init__.py
atri_utils/background_switch.py
atri_utils/decodeCharts.py
atri_utils/media_response.py
atri_utils/pagination.py
atri_utils/test_sample.py
atri_utils/uploaded_files.py
atri_utils/write_table.py
atri_utils-0.0.67.dist-info/METADATA
atri_utils-0.0.67.dist-info/WHEEL
atri_utils-0.0.67.dist-info/top_level.txt
atri_utils-0.0.67.dist-info/RECORD
