Metadata-Version: 2.1
Name: atri-utils
Version: 0.0.67
Summary: Utility functions for Atri framwork backend/controllers.
Home-page: https://atrilabs.com
Author: Atri Labs
Author-email: shyam.swaroop@atrilabs.com
License: GPLv3
Project-URL: Source, https://github.com/Atri-Labs/atri_utils.git
Requires-Python: >=3.7
